{
  "_format": "hh-sol-cache-2",
  "files": {
    "/home/auryn/git/poster/contracts/IPoster.sol": {
      "lastModificationDate": 1627488826803,
      "contentHash": "5fdf3cb0a1ea95c12114ecd8e4eeec45",
      "sourceName": "contracts/IPoster.sol",
      "solcConfig": {
        "version": "0.8.0",
        "settings": {
          "optimizer": {
            "enabled": false,
            "runs": 200
          },
          "outputSelection": {
            "*": {
              "*": [
                "abi",
                "evm.bytecode",
                "evm.deployedBytecode",
                "evm.methodIdentifiers"
              ],
              "": [
                "ast"
              ]
            }
          }
        }
      },
      "imports": [],
      "versionPragmas": [
        "0.8.0"
      ],
      "artifacts": [
        "IPoster"
      ]
    },
    "/home/auryn/git/poster/contracts/Poster.sol": {
      "lastModificationDate": 1627489119031,
      "contentHash": "4492ada0422025ef35bbe9e423721c28",
      "sourceName": "contracts/Poster.sol",
      "solcConfig": {
        "version": "0.8.0",
        "settings": {
          "optimizer": {
            "enabled": false,
            "runs": 200
          },
          "outputSelection": {
            "*": {
              "*": [
                "abi",
                "evm.bytecode",
                "evm.deployedBytecode",
                "evm.methodIdentifiers"
              ],
              "": [
                "ast"
              ]
            }
          }
        }
      },
      "imports": [],
      "versionPragmas": [
        "0.8.0"
      ],
      "artifacts": [
        "Poster"
      ]
    }
  }
}
